<?xml version="1.0" encoding="utf-8" ?>
<c2layout>
    <name>Inicio_menu</name>
    <sid>5335129693182129</sid>
    <event-sheet>Event Inicio</event-sheet>
    <size>
        <width>1024</width>
        <height>600</height>
    </size>
    <margins>
        <horizontal>500</horizontal>
        <vertical>500</vertical>
    </margins>
    <unbounded-scrolling>0</unbounded-scrolling>
    <layers>
        <layer name="Fondo1" sid="2174922244620603">
            <initially-visible>1</initially-visible>
            <background-color>255,255,255</background-color>
            <transparent>0</transparent>
            <parallax>
                <x>1</x>
                <y>1</y>
            </parallax>
            <zoom-rate>1</zoom-rate>
            <opacity>1</opacity>
            <force-own-texture>0</force-own-texture>
            <global>0</global>
            <use-render-cells>0</use-render-cells>
            <blend-mode>0</blend-mode>
            <effect-fallback>0</effect-fallback>
            <instances>
                <instance type="Fondo1" uid="17">
                    <properties>
                        <initial-visibility>Visible</initial-visibility>
                        <hotspot>Top-left</hotspot>
                    </properties>
                    <blend-mode>0</blend-mode>
                    <effect-fallback>0</effect-fallback>
                    <world>
                        <x>0</x>
                        <y>0</y>
                        <z>0</z>
                        <width>1024</width>
                        <height>600</height>
                        <depth>0</depth>
                        <hotspotX>0</hotspotX>
                        <hotspotY>0</hotspotY>
                        <angle>0</angle>
                        <opacity>1</opacity>
                    </world>
                </instance>
                <instance type="btn_volver" uid="23">
                    <properties>
                        <initial-visibility>Visible</initial-visibility>
                        <initial-animation>Default</initial-animation>
                        <initial-frame>0</initial-frame>
                        <collisions>Enabled</collisions>
                    </properties>
                    <blend-mode>0</blend-mode>
                    <effect-fallback>0</effect-fallback>
                    <world>
                        <x>79</x>
                        <y>542</y>
                        <z>0</z>
                        <width>100</width>
                        <height>100</height>
                        <depth>0</depth>
                        <hotspotX>0.5</hotspotX>
                        <hotspotY>0.5</hotspotY>
                        <angle>0</angle>
                        <opacity>1</opacity>
                    </world>
                </instance>
                <instance type="cur_normal" uid="390">
                    <properties>
                        <initial-visibility>Visible</initial-visibility>
                        <initial-animation>Default</initial-animation>
                        <initial-frame>0</initial-frame>
                        <collisions>Enabled</collisions>
                    </properties>
                    <blend-mode>0</blend-mode>
                    <effect-fallback>0</effect-fallback>
                    <world>
                        <x>315</x>
                        <y>674</y>
                        <z>0</z>
                        <width>32</width>
                        <height>32</height>
                        <depth>0</depth>
                        <hotspotX>0</hotspotX>
                        <hotspotY>0</hotspotY>
                        <angle>0</angle>
                        <opacity>1</opacity>
                    </world>
                </instance>
                <instance type="cur_sobre" uid="391">
                    <properties>
                        <initial-visibility>Visible</initial-visibility>
                        <initial-animation>Default</initial-animation>
                        <initial-frame>0</initial-frame>
                        <collisions>Enabled</collisions>
                    </properties>
                    <blend-mode>0</blend-mode>
                    <effect-fallback>0</effect-fallback>
                    <world>
                        <x>381</x>
                        <y>674</y>
                        <z>0</z>
                        <width>32</width>
                        <height>32</height>
                        <depth>0</depth>
                        <hotspotX>0</hotspotX>
                        <hotspotY>0</hotspotY>
                        <angle>0</angle>
                        <opacity>1</opacity>
                    </world>
                </instance>
                <instance type="Sprite4" uid="545">
                    <properties>
                        <initial-visibility>Visible</initial-visibility>
                        <initial-animation>Default</initial-animation>
                        <initial-frame>0</initial-frame>
                        <collisions>Enabled</collisions>
                    </properties>
                    <blend-mode>0</blend-mode>
                    <effect-fallback>0</effect-fallback>
                    <world>
                        <x>512</x>
                        <y>304</y>
                        <z>0</z>
                        <width>618</width>
                        <height>577</height>
                        <depth>0</depth>
                        <hotspotX>0.500372827</hotspotX>
                        <hotspotY>0.5</hotspotY>
                        <angle>0</angle>
                        <opacity>1</opacity>
                    </world>
                </instance>
                <instance type="Introduccion" uid="18">
                    <properties>
                        <initial-visibility>Visible</initial-visibility>
                        <initial-animation>Default</initial-animation>
                        <initial-frame>0</initial-frame>
                        <collisions>Enabled</collisions>
                    </properties>
                    <blend-mode>0</blend-mode>
                    <effect-fallback>0</effect-fallback>
                    <world>
                        <x>443</x>
                        <y>-248</y>
                        <z>0</z>
                        <width>201</width>
                        <height>59</height>
                        <depth>0</depth>
                        <hotspotX>0.5</hotspotX>
                        <hotspotY>0.50746268</hotspotY>
                        <angle>0</angle>
                        <opacity>1</opacity>
                    </world>
                </instance>
                <instance type="Opcion1" uid="19">
                    <properties>
                        <initial-visibility>Visible</initial-visibility>
                        <initial-animation>Default</initial-animation>
                        <initial-frame>0</initial-frame>
                        <collisions>Enabled</collisions>
                    </properties>
                    <blend-mode>0</blend-mode>
                    <effect-fallback>0</effect-fallback>
                    <world>
                        <x>351</x>
                        <y>143</y>
                        <z>0</z>
                        <width>110</width>
                        <height>110</height>
                        <depth>0</depth>
                        <hotspotX>0.503816783</hotspotX>
                        <hotspotY>0.503816783</hotspotY>
                        <angle>0</angle>
                        <opacity>0.800000012</opacity>
                    </world>
                </instance>
                <instance type="Opcion2" uid="20">
                    <properties>
                        <initial-visibility>Visible</initial-visibility>
                        <initial-animation>Default</initial-animation>
                        <initial-frame>0</initial-frame>
                        <collisions>Enabled</collisions>
                    </properties>
                    <blend-mode>0</blend-mode>
                    <effect-fallback>0</effect-fallback>
                    <world>
                        <x>685</x>
                        <y>146</y>
                        <z>0</z>
                        <width>110</width>
                        <height>110</height>
                        <depth>0</depth>
                        <hotspotX>0.503816783</hotspotX>
                        <hotspotY>0.503816783</hotspotY>
                        <angle>0</angle>
                        <opacity>0.800000012</opacity>
                    </world>
                </instance>
                <instance type="Opcion3" uid="21">
                    <properties>
                        <initial-visibility>Visible</initial-visibility>
                        <initial-animation>Default</initial-animation>
                        <initial-frame>0</initial-frame>
                        <collisions>Enabled</collisions>
                    </properties>
                    <blend-mode>0</blend-mode>
                    <effect-fallback>0</effect-fallback>
                    <world>
                        <x>348</x>
                        <y>462</y>
                        <z>0</z>
                        <width>110</width>
                        <height>110</height>
                        <depth>0</depth>
                        <hotspotX>0.503816783</hotspotX>
                        <hotspotY>0.503816783</hotspotY>
                        <angle>0</angle>
                        <opacity>0.800000012</opacity>
                    </world>
                </instance>
                <instance type="Opcion4" uid="22">
                    <properties>
                        <initial-visibility>Visible</initial-visibility>
                        <initial-animation>Default</initial-animation>
                        <initial-frame>0</initial-frame>
                        <collisions>Enabled</collisions>
                    </properties>
                    <blend-mode>0</blend-mode>
                    <effect-fallback>0</effect-fallback>
                    <world>
                        <x>668</x>
                        <y>450</y>
                        <z>0</z>
                        <width>110</width>
                        <height>110</height>
                        <depth>0</depth>
                        <hotspotX>0.503816783</hotspotX>
                        <hotspotY>0.503816783</hotspotY>
                        <angle>0</angle>
                        <opacity>0.800000012</opacity>
                    </world>
                </instance>
                <instance type="txt_seleccion" uid="546">
                    <properties>
                        <character-width>31</character-width>
                        <character-height>36</character-height>
                        <character-set>ABCDEFGHIJKLMNOPQRSTUVWXYZabcdefghijklmnopqrstuvwxyz0123456789.,;:?!-_~#&quot;&apos;&amp;()[]|`\/@°+=*$£€&lt;&gt;</character-set>
                        <text>MENU</text>
                        <scale>1</scale>
                        <initial-visibility>Visible</initial-visibility>
                        <horizontal-alignment>Center</horizontal-alignment>
                        <vertical-alignment>Top</vertical-alignment>
                        <hotspot>Top-left</hotspot>
                        <wrapping>Word</wrapping>
                        <character-spacing>-10</character-spacing>
                        <line-height>0</line-height>
                    </properties>
                    <blend-mode>0</blend-mode>
                    <effect-fallback>0</effect-fallback>
                    <world>
                        <x>191</x>
                        <y>273</y>
                        <z>0</z>
                        <width>658</width>
                        <height>63</height>
                        <depth>0</depth>
                        <hotspotX>0</hotspotX>
                        <hotspotY>0</hotspotY>
                        <angle>0</angle>
                        <opacity>1</opacity>
                    </world>
                </instance>
            </instances>
            <effects />
        </layer>
        <layer name="Principal" sid="4812272958022656">
            <initially-visible>1</initially-visible>
            <background-color>255,255,255</background-color>
            <transparent>1</transparent>
            <parallax>
                <x>1</x>
                <y>1</y>
            </parallax>
            <zoom-rate>1</zoom-rate>
            <opacity>1</opacity>
            <force-own-texture>0</force-own-texture>
            <global>0</global>
            <use-render-cells>0</use-render-cells>
            <blend-mode>0</blend-mode>
            <effect-fallback>0</effect-fallback>
            <instances />
            <effects />
        </layer>
        <layer name="Menu" sid="7926060185493544">
            <initially-visible>1</initially-visible>
            <background-color>255,255,255</background-color>
            <transparent>1</transparent>
            <parallax>
                <x>1</x>
                <y>1</y>
            </parallax>
            <zoom-rate>1</zoom-rate>
            <opacity>1</opacity>
            <force-own-texture>0</force-own-texture>
            <global>0</global>
            <use-render-cells>0</use-render-cells>
            <blend-mode>0</blend-mode>
            <effect-fallback>0</effect-fallback>
            <instances />
            <effects />
        </layer>
    </layers>
    <nonworld-instances />
    <effects>
        <effect-type name="HighlightShadow">
            <effect id="highlightshadow" />
            <effect-instance type="HighlightShadow">
                <parameters>
                    <highlight-factor>1</highlight-factor>
                    <shadow-factor>0</shadow-factor>
                </parameters>
            </effect-instance>
        </effect-type>
    </effects>
</c2layout>
